s7/__init__.py
s7/cli.py
s7/s7.py
s7-0.1.0.dist-info/entry_points.txt
s7-0.1.0.dist-info/LICENSE
s7-0.1.0.dist-info/WHEEL
s7-0.1.0.dist-info/METADATA
s7-0.1.0.dist-info/RECORD
