Metadata-Version: 2.1
Name: s7
Version: 0.1.0
Summary: Top-level package for Seven.
Home-page: https://github.com/dweemx/s7
License: MIT
Author: Maxime De Waegeneer
Author-email: maxime.dewaegeneer@kuleuven.vib.be
Classifier: Development Status :: 2 - Pre-Alpha
Classifier: Intended Audience :: Developers
Classifier: License :: OSI Approved :: MIT License
Classifier: Natural Language :: English
Classifier: Programming Language :: Python :: 2
Classifier: Programming Language :: Python :: 2.7
Classifier: Programming Language :: Python :: 3
Classifier: Programming Language :: Python :: 3.4
Classifier: Programming Language :: Python :: 3.5
Classifier: Programming Language :: Python :: 3.6
Classifier: Programming Language :: Python :: 3.7
Classifier: Programming Language :: Python :: 3.8
Requires-Dist: click
